{"noah.sanchez@me.com": 2585, "michael.hall@dropbox.net": 2974, "olivia.wright@gmail.com": 3239, "isabella.jackson@amerisave.com": 3123, "hannah.martin@dropbox.net": 3354, "madison.lewis@gmail.com": 3373, "abigail.smith@amerisave.com": 3149, "chloe.garcia@dropbox.net": 2900, "daniel.rodriguez@amerisave.com": 3472, "taylor.adams@gmail.com": 2996, "sarah.green@amerisave.com": 3191, "liam.gonzalez@me.com": 3156, "grace.moore@gmail.com": 3160, "nicholas.allen@microsoft.com": 2994, "tyler.nelson@microsoft.com": 3377, "andrew.miller@gmail.com": 2985, "samantha.scott@me.com": 3336, "jackson.white@gmail.com": 3137, "nathan.young@microsoft.com": 3052, "emma.thomas@me.com": 3116, "alexander.williams@gmail.com": 2750, "sophia.baker@dropbox.net": 2718, "elizabeth.martinez@dropbox.net": 3054, "logan.clark@dropbox.net": 2948, "lily.harris@gmail.com": 3050, "emily.taylor@gmail.com": 3222, "matthew.walker@amerisave.com": 3404, "jacob.lopez@dropbox.net": 2945, "aiden.johnson@microsoft.com": 2827, "alexis.brown@microsoft.com": 3047, "alyssa.jones@amerisave.com": 3254, "mia.perez@me.com": 3358, "ella.anderson@dropbox.net": 3093, "mason.robinson@amerisave.com": 3632, "dylan.wilson@gmail.com": 3049, "ava.davis@gmail.com": 2961, "jack.thompson@me.com": 3397, "ryan.king@dropbox.net": 3189, "ethan.hernandez@microsoft.com": 2875, "joshua.lee@gmail.com": 3175}